edn_format/__init__.py
edn_format/char.py
edn_format/compat.py
edn_format/edn_dump.py
edn_format/edn_lex.py
edn_format/edn_parse.py
edn_format/exceptions.py
edn_format/immutable_dict.py
edn_format/immutable_list.py
edn_format/parsetab.py
edn_format-0.7.4.dist-info/LICENSE.txt
edn_format-0.7.4.dist-info/METADATA
edn_format-0.7.4.dist-info/WHEEL
edn_format-0.7.4.dist-info/top_level.txt
edn_format-0.7.4.dist-info/RECORD
