Metadata-Version: 2.1
Name: edn-format
Version: 0.7.4
Summary: EDN format reader and writer in Python
Home-page: https://github.com/swaroopch/edn_format
Author: Swaroop C H
Author-email: swaroop@swaroopch.com
License: Apache 2.0
Platform: UNKNOWN
Classifier: Development Status :: 5 - Production/Stable
Classifier: Intended Audience :: Developers
Classifier: License :: OSI Approved :: Apache Software License
Classifier: Topic :: Software Development
Classifier: Programming Language :: Python
Classifier: Programming Language :: Python :: 2
Classifier: Programming Language :: Python :: 3
Classifier: Operating System :: OS Independent
Requires-Dist: ply (>=3.10)
Requires-Dist: pyRFC3339 (>=0.2)
Requires-Dist: pytz (>=2016.10)
